pycontree-1.0.5.dist-info/METADATA
pycontree-1.0.5.dist-info/LICENSE
pycontree-1.0.5.dist-info/top_level.txt
pycontree-1.0.5.dist-info/WHEEL
pycontree-1.0.5.dist-info/RECORD
pycontree/base.py
pycontree/ccontree.cpython-312-x86_64-linux-gnu.so
pycontree/__init__.py
pycontree/export.py
