Metadata-Version: 2.1
Name: pycontree
Version: 1.0.5
Summary: Python Wrapper ConTree: Optimal Decision Trees for Continuous Feature Data
Author-email: "Cătălin E. Briţa" <C.E.Brita@student.tudelft.nl>, "Jacobus G. M. van der Linden" <J.G.M.vanderLinden@tudelft.nl>, Emir Demirović <E.Demirovic@tudelft.nl>
Maintainer-email: "Cătălin E. Briţa" <C.E.Brita@student.tudelft.nl>, "Jacobus G. M. van der Linden" <J.G.M.vanderLinden@tudelft.nl>
License: Copyright 2024 Cătălin E. Briţa, Jacobus G. M. van der Linden, Delft University of Technology
Project-URL: Repository, https://github.com/consol-lab/contree
Classifier: Programming Language :: Python :: 3
Classifier: License :: OSI Approved :: MIT License
Classifier: Operating System :: OS Independent
Requires-Python: >=3.10
License-File: LICENSE
Requires-Dist: pandas >=1.0.0
Requires-Dist: numpy >=1.18.0
Requires-Dist: scikit-learn >=1.6.0
Requires-Dist: typing-extensions >=4.0.0
